sequential_executor/__init__.py
sequential_executor-1.0.0.dist-info/LICENSE
sequential_executor-1.0.0.dist-info/METADATA
sequential_executor-1.0.0.dist-info/WHEEL
sequential_executor-1.0.0.dist-info/top_level.txt
sequential_executor-1.0.0.dist-info/RECORD
