Metadata-Version: 2.1
Name: sequential-executor
Version: 1.0.0
Summary: A concurrent.futures.Executor implementation that performs sequential execution
Home-page: https://github.com/QuiNovas/sequential-executor
Author: Joseph Wortmann
Author-email: jwortmann@quinovas.com
License: Apache 2.0
Platform: UNKNOWN
Classifier: Development Status :: 4 - Beta
Classifier: Intended Audience :: Developers
Classifier: License :: OSI Approved :: Apache Software License
Classifier: Programming Language :: Python :: 3.9
Requires-Python: >=3.9
License-File: LICENSE
